{
    "eng": {
        "word": "Yokel",
        "pronunciation": "/ˈjoʊkəl/",
        "partOfSpeech": "noun",
        "definition": "an uneducated and unsophisticated person from the countryside.",
        "examples": [
            "He was tired of being treated like a yokel just because he lived in the country.",
            "The movie portrayed the character as a simple yokel who finds success in the city.",
            "The city slickers made fun of the yokel's naive ways."
        ],
        "dateUsed": 1780540982
    },
    "hin": {
        "word": "कठिनाई",
        "pronunciation": "/kʌtʰɪnɑːi/",
        "partOfSpeech": "noun",
        "definition": "difficulty or hardship",
        "examples": [
            "हमने कठिनाईयों का सामना किया, लेकिन हमने हार नहीं मानी।",
            "मैं कठिनाई के बीना सीखने के लिए प्रयास करता हूँ।",
            "उन्होंने कठिनाईयों के बावजूद अपने लक्ष्य को प्राप्त किया।"
        ],
        "dateUsed": 1780540982
    }
}
